[{"class_weight": 1.2000000000000002, "metric": "cosine", "n_neighbors": 174, "weights": "distance"}, {"class_weight": 1.4000000000000004, "metric": "chebyshev", "n_neighbors": 140, "weights": "uniform"}, {"class_weight": 1.4000000000000004, "metric": "chebyshev", "n_neighbors": 130, "weights": "distance"}, {"class_weight": 1.4000000000000004, "metric": "canberra", "n_neighbors": 180, "weights": "uniform"}, {"class_weight": 1.4000000000000004, "metric": "canberra", "n_neighbors": 158, "weights": "uniform"}, {"class_weight": 1.4000000000000004, "metric": "canberra", "n_neighbors": 196, "weights": "distance"}, {"class_weight": 1.4000000000000004, "metric": "chebyshev", "n_neighbors": 134, "weights": "distance"}, {"class_weight": 1.4000000000000004, "metric": "canberra", "n_neighbors": 148, "weights": "uniform"}, {"class_weight": 1.4000000000000004, "metric": "chebyshev", "n_neighbors": 176, "weights": "distance"}, {"class_weight": 1.4000000000000004, "metric": "canberra", "n_neighbors": 196, "weights": "distance"}, {"class_weight": 1.4000000000000004, "metric": "chebyshev", "n_neighbors": 132, "weights": "distance"}, {"class_weight": 1.2000000000000002, "metric": "cosine", "n_neighbors": 198, "weights": "uniform"}, {"class_weight": 1.4000000000000004, "metric": "cosine", "n_neighbors": 188, "weights": "uniform"}, {"class_weight": 1.4000000000000004, "metric": "cosine", "n_neighbors": 182, "weights": "uniform"}, {"class_weight": 1.4000000000000004, "metric": "canberra", "n_neighbors": 198, "weights": "uniform"}, {"class_weight": 1.4000000000000004, "metric": "canberra", "n_neighbors": 192, "weights": "uniform"}, {"class_weight": 1.4000000000000004, "metric": "canberra", "n_neighbors": 162, "weights": "distance"}, {"class_weight": 1.4000000000000004, "metric": "chebyshev", "n_neighbors": 140, "weights": "distance"}, {"class_weight": 1.4000000000000004, "metric": "cosine", "n_neighbors": 162, "weights": "uniform"}, {"class_weight": 1.4000000000000004, "metric": "chebyshev", "n_neighbors": 128, "weights": "distance"}, {"class_weight": 1.4000000000000004, "metric": "chebyshev", "n_neighbors": 146, "weights": "distance"}, {"class_weight": 1.4000000000000004, "metric": "chebyshev", "n_neighbors": 140, "weights": "uniform"}, {"class_weight": 1.4000000000000004, "metric": "cosine", "n_neighbors": 184, "weights": "uniform"}, {"class_weight": 1.4000000000000004, "metric": "canberra", "n_neighbors": 194, "weights": "uniform"}, {"class_weight": 1.4000000000000004, "metric": "chebyshev", "n_neighbors": 156, "weights": "distance"}, {"class_weight": 1.4000000000000004, "metric": "chebyshev", "n_neighbors": 134, "weights": "distance"}, {"class_weight": 1.4000000000000004, "metric": "chebyshev", "n_neighbors": 122, "weights": "uniform"}, {"class_weight": 1.4000000000000004, "metric": "cosine", "n_neighbors": 186, "weights": "uniform"}, {"class_weight": 1.4000000000000004, "metric": "chebyshev", "n_neighbors": 136, "weights": "uniform"}, {"class_weight": 1.4000000000000004, "metric": "cosine", "n_neighbors": 194, "weights": "distance"}, {"class_weight": 1.2000000000000002, "metric": "cosine", "n_neighbors": 170, "weights": "distance"}, {"class_weight": 1.4000000000000004, "metric": "chebyshev", "n_neighbors": 172, "weights": "distance"}, {"class_weight": 1.4000000000000004, "metric": "canberra", "n_neighbors": 164, "weights": "distance"}, {"class_weight": 1.4000000000000004, "metric": "canberra", "n_neighbors": 198, "weights": "uniform"}, {"class_weight": 1.4000000000000004, "metric": "chebyshev", "n_neighbors": 130, "weights": "distance"}, {"class_weight": 1.2000000000000002, "metric": "cosine", "n_neighbors": 136, "weights": "uniform"}, {"class_weight": 1.4000000000000004, "metric": "cosine", "n_neighbors": 154, "weights": "distance"}, {"class_weight": 1.4000000000000004, "metric": "braycurtis", "n_neighbors": 196, "weights": "uniform"}, {"class_weight": 1.4000000000000004, "metric": "cosine", "n_neighbors": 190, "weights": "uniform"}, {"class_weight": 1.4000000000000004, "metric": "cosine", "n_neighbors": 190, "weights": "uniform"}, {"class_weight": 1.4000000000000004, "metric": "braycurtis", "n_neighbors": 172, "weights": "distance"}, {"class_weight": 1.4000000000000004, "metric": "cosine", "n_neighbors": 196, "weights": "uniform"}]